constructive_geometries/__init__.py
constructive_geometries/calculate_areas.py
constructive_geometries/cg.py
constructive_geometries/compatibility.py
constructive_geometries/geomatcher.py
constructive_geometries/data/areas.json
constructive_geometries/data/europe.json
constructive_geometries/data/faces.gpkg
constructive_geometries/data/faces.json
constructive_geometries-1.0.dist-info/LICENSE
constructive_geometries-1.0.dist-info/METADATA
constructive_geometries-1.0.dist-info/WHEEL
constructive_geometries-1.0.dist-info/top_level.txt
constructive_geometries-1.0.dist-info/RECORD
